{
  "info": {
    "_postman_id": "bb3be35e-39c6-4bef-becf-792e0e8054d7",
    "name": "Lab 04 : Student REST API",
    "schema": "https://schema.getpostman.com/json/collection/v2.1.0/collection.json",
    "_exporter_id": "55017231",
    "_collection_link": "https://go.postman.co/collection/55017231-bb3be35e-39c6-4bef-becf-792e0e8054d7?source=collection_link"
  },
  "item": [
    {
      "name": "Get All Students",
      "request": {
        "method": "GET",
        "header": [],
        "url": {
          "raw": "{{baseUrl}}/api/students",
          "host": [
            "{{baseUrl}}"
          ],
          "path": [
            "api",
            "students"
          ]
        }
      },
      "response": []
    },
    {
      "name": "Get Student by ID",
      "request": {
        "method": "GET",
        "header": [],
        "url": {
          "raw": "{{baseUrl}}/api/students/1",
          "host": [
            "{{baseUrl}}"
          ],
          "path": [
            "api",
            "students",
            "1"
          ]
        }
      },
      "response": []
    },
    {
      "name": "Get Student Not Found",
      "request": {
        "method": "GET",
        "header": [],
        "url": {
          "raw": "{{baseUrl}}/api/students/999",
          "host": [
            "{{baseUrl}}"
          ],
          "path": [
            "api",
            "students",
            "999"
          ]
        }
      },
      "response": []
    },
    {
      "name": "Create Student",
      "request": {
        "method": "POST",
        "header": [],
        "body": {
          "mode": "raw",
          "raw": "{\n    \"name\": \"Sneha Patel\",\n    \"email\": \"sneha@example.com\",\n    \"branch\": \"Information Technology\",\n    \"year\": 1\n}\n",
          "options": {
            "raw": {
              "language": "json"
            }
          }
        },
        "url": {
          "raw": "{{baseUrl}}/api/students",
          "host": [
            "{{baseUrl}}"
          ],
          "path": [
            "api",
            "students"
          ]
        }
      },
      "response": []
    },
    {
      "name": "Update Student",
      "request": {
        "method": "PUT",
        "header": [],
        "body": {
          "mode": "raw",
          "raw": "{\n    \"name\": \"Rahul Sharma\",\n    \"email\": \"rahul.sharma@example.com\",\n    \"branch\": \"Computer Science\",\n    \"year\": 3\n}",
          "options": {
            "raw": {
              "language": "json"
            }
          }
        },
        "url": {
          "raw": "{{baseUrl}}/api/students/1",
          "host": [
            "{{baseUrl}}"
          ],
          "path": [
            "api",
            "students",
            "1"
          ]
        }
      },
      "response": []
    },
    {
      "name": "Delete Student",
      "request": {
        "method": "DELETE",
        "header": [],
        "url": {
          "raw": "{{baseUrl}}/api/students/1",
          "host": [
            "{{baseUrl}}"
          ],
          "path": [
            "api",
            "students",
            "1"
          ]
        }
      },
      "response": []
    },
    {
      "name": "Get Deleted Student",
      "request": {
        "method": "GET",
        "header": [],
        "url": {
          "raw": "{{baseUrl}}/api/students/1",
          "host": [
            "{{baseUrl}}"
          ],
          "path": [
            "api",
            "students",
            "1"
          ]
        }
      },
      "response": []
    }
  ]
}